gw_agn_watcher/__init__.py
gw_agn_watcher/classifiers.py
gw_agn_watcher/db.py
gw_agn_watcher/detections.py
gw_agn_watcher/divide.py
gw_agn_watcher/extinction.py
gw_agn_watcher/findminclust.py
gw_agn_watcher/get_public_alerts.py
gw_agn_watcher/main_pipeline.py
gw_agn_watcher/mainquery.py
gw_agn_watcher/match_milliquas.py
gw_agn_watcher/radecligo.py
gw_agn_watcher/redshift.py
gw_agn_watcher-0.1.3.dist-info/licenses/LICENSE
gw_agn_watcher-0.1.3.dist-info/METADATA
gw_agn_watcher-0.1.3.dist-info/WHEEL
gw_agn_watcher-0.1.3.dist-info/top_level.txt
gw_agn_watcher-0.1.3.dist-info/RECORD
