Metadata-Version: 2.4
Name: gw_agn_watcher
Version: 0.1.3
Summary: Python tools for GW AGN follow-up
Home-page: https://github.com/Hemanthb1/GW_AGN_watcher
Author: Hemanth Kumar
Author-email: hemanth.bommireddy195@gmail.com
License: MIT
Classifier: Programming Language :: Python :: 3
Classifier: License :: OSI Approved :: MIT License
Classifier: Operating System :: OS Independent
Requires-Python: >=3.8
License-File: LICENSE
Requires-Dist: numpy
Requires-Dist: astropy
Requires-Dist: matplotlib
Requires-Dist: scipy
Requires-Dist: requests
Requires-Dist: pandas
Requires-Dist: astroquery
Requires-Dist: alphashape
Requires-Dist: psycopg2
Requires-Dist: requests
Requires-Dist: ephem
Requires-Dist: dustmaps
Requires-Dist: dust_extinction
Requires-Dist: ligo.skymap
Dynamic: author
Dynamic: author-email
Dynamic: classifier
Dynamic: description
Dynamic: description-content-type
Dynamic: home-page
Dynamic: license
Dynamic: license-file
Dynamic: requires-dist
Dynamic: requires-python
Dynamic: summary
